chat_gpt/__init__.py
chat_gpt/config.py
chat_gpt/main.py
chat_gpt/commands/__init__.py
chat_gpt/commands/chat.py
chat_gpt/commands/rag.py
chat_gpt/commands/youtube.py
chat_gpt/utils/__init__.py
chat_gpt/utils/ingestor.py
chat_gpt/utils/weaviate_vectorstore.py
custom_chat_gpt-0.6.0.dist-info/METADATA
custom_chat_gpt-0.6.0.dist-info/WHEEL
custom_chat_gpt-0.6.0.dist-info/entry_points.txt
custom_chat_gpt-0.6.0.dist-info/RECORD
