Metadata-Version: 2.3
Name: custom-chat-gpt
Version: 0.6.0
Summary: Use chapgpt from your terminal
Requires-Python: >=3.12
Requires-Dist: langchain-anthropic>=0.2.3
Requires-Dist: langchain-community>=0.3.2
Requires-Dist: langchain-openai>=0.2.2
Requires-Dist: langchain>=0.3.3
Requires-Dist: openai>=1.51.2
Requires-Dist: rich>=13.9.2
Requires-Dist: typer>=0.12.5
Requires-Dist: youtube-transcript-api>=0.6.2
